tinymlx/__init__.py
tinymlx/gemm.py
tinymlx/helpers.py
tinymlx-0.1.0.dist-info/METADATA
tinymlx-0.1.0.dist-info/WHEEL
tinymlx-0.1.0.dist-info/top_level.txt
tinymlx-0.1.0.dist-info/RECORD
