Metadata-Version: 2.4
Name: tinymlx
Version: 0.1.0
Summary: TinyML — minimal, high-performance Machine Learning library.
Author: Prasad Raju G
Requires-Python: >=3.13
Requires-Dist: numpy
Provides-Extra: dev
Requires-Dist: matplotlib>=3.10.8; extra == "dev"
